QBanHuanchongquYichuJiaochengFix1/README.md
QBanHuanchongquYichuJiaochengFix1/__init__.py
QBanHuanchongquYichuJiaochengFix1/__main__.py
QBanHuanchongquYichuJiaochengFix1/file.epub
QBanHuanchongquYichuJiaochengFix1/index.html
QBanHuanchongquYichuJiaochengFix1/css/__init__.py
QBanHuanchongquYichuJiaochengFix1/css/annotations.css
QBanHuanchongquYichuJiaochengFix1/css/main.css
QBanHuanchongquYichuJiaochengFix1/css/normalize.css
QBanHuanchongquYichuJiaochengFix1/css/popup.css
QBanHuanchongquYichuJiaochengFix1/font/__init__.py
QBanHuanchongquYichuJiaochengFix1/font/fontello.eot
QBanHuanchongquYichuJiaochengFix1/font/fontello.svg
QBanHuanchongquYichuJiaochengFix1/font/fontello.ttf
QBanHuanchongquYichuJiaochengFix1/font/fontello.woff
QBanHuanchongquYichuJiaochengFix1/img/__init__.py
QBanHuanchongquYichuJiaochengFix1/img/annotator-glyph-sprite.png
QBanHuanchongquYichuJiaochengFix1/img/annotator-icon-sprite.png
QBanHuanchongquYichuJiaochengFix1/img/apple-touch-icon.png
QBanHuanchongquYichuJiaochengFix1/img/cancelfullscreen.png
QBanHuanchongquYichuJiaochengFix1/img/close.png
QBanHuanchongquYichuJiaochengFix1/img/fullscreen.png
QBanHuanchongquYichuJiaochengFix1/img/loader.gif
QBanHuanchongquYichuJiaochengFix1/img/menu-icon.png
QBanHuanchongquYichuJiaochengFix1/img/save.png
QBanHuanchongquYichuJiaochengFix1/img/saved.png
QBanHuanchongquYichuJiaochengFix1/img/settings-s.png
QBanHuanchongquYichuJiaochengFix1/img/settings.png
QBanHuanchongquYichuJiaochengFix1/img/star.png
QBanHuanchongquYichuJiaochengFix1/js/__init__.py
QBanHuanchongquYichuJiaochengFix1/js/epub.js
QBanHuanchongquYichuJiaochengFix1/js/epub.min.js
QBanHuanchongquYichuJiaochengFix1/js/epub.min.map
QBanHuanchongquYichuJiaochengFix1/js/hooks.min.js
QBanHuanchongquYichuJiaochengFix1/js/hooks.min.map
QBanHuanchongquYichuJiaochengFix1/js/reader.js
QBanHuanchongquYichuJiaochengFix1/js/reader.js.map
QBanHuanchongquYichuJiaochengFix1/js/reader.min.js
QBanHuanchongquYichuJiaochengFix1/js/reader.min.map
q_ban_huanchongqu_yichu_jiaocheng_fix1-2024.3.2.0.dist-info/METADATA
q_ban_huanchongqu_yichu_jiaocheng_fix1-2024.3.2.0.dist-info/WHEEL
q_ban_huanchongqu_yichu_jiaocheng_fix1-2024.3.2.0.dist-info/entry_points.txt
q_ban_huanchongqu_yichu_jiaocheng_fix1-2024.3.2.0.dist-info/top_level.txt
q_ban_huanchongqu_yichu_jiaocheng_fix1-2024.3.2.0.dist-info/RECORD
